setup.py
chp/components.py
chp/entry_point.py
chp/js.py
chp/mdc.py
chp/pyreact.py
chp/store.py
chp.egg-info/PKG-INFO
chp.egg-info/SOURCES.txt
chp.egg-info/dependency_links.txt
chp.egg-info/entry_points.txt
chp.egg-info/requires.txt
chp.egg-info/top_level.txt
chp/django/mdc.py